{
    "MatchedRegions": [
        {
            "start_time": "00:00:01,447",
            "end_time": "00:00:01,964",
            "transcript": "the energies.",
            "MatchedRegion": []
        }
    ],
    "MatchedSlides": [
        {
            "slide": "PART_0000_MEOJKJ3n58NsNxBI",
            "Score": 0.6054133176803589
        },
        {
            "slide": "PART_0001_pXxJk9ctFPwTH6UL",
            "Score": 0.7212560176849365
        },
        {
            "slide": "PART_0005_QY40g5FaK4rHuqfC",
            "Score": 0.7281044125556946
        }
    ]
}