{
    "MatchedRegions": [
        {
            "start_time": "00:00:01,811",
            "end_time": "00:00:10,218",
            "transcript": "Therefore, we believe that we need more aspects to verify this metric can be used to quantify concepts learned by a DNN.",
            "MatchedRegion": [
                {
                    "Text": "Sparsity: The DNN's inference on a specific sample is supposed to be concisely explained by a small number of salient concepts.",
                    "BoundingBox": {
                        "Width": 0.7248382568359375,
                        "Height": 0.07416196167469025,
                        "Left": 0.13706625998020172,
                        "Top": 0.3595198392868042
                    },
                    "BlockType": "LAYOUT_TEXT",
                    "Id": "fc0b1e1a-123d-4107-97a6-79030d085a66",
                    "Score": 0.8535122871398926
                },
                {
                    "Text": "Model-wise transferability: Whether concepts extracted from a DNN can be transferred to another DNN trained for the same task.",
                    "BoundingBox": {
                        "Width": 0.7245076298713684,
                        "Height": 0.06868676096200943,
                        "Left": 0.13720358908176422,
                        "Top": 0.55068439245224
                    },
                    "BlockType": "LAYOUT_TEXT",
                    "Id": "48346a48-fc77-42d8-ac0b-cc4d2c370219",
                    "Score": 0.8805666565895081
                }
            ]
        },
        {
            "start_time": "00:00:11,059",
            "end_time": "00:00:13,542",
            "transcript": "Specifically, we propose four perspectives.",
            "MatchedRegion": [
                {
                    "Text": "Sparsity: The DNN's inference on a specific sample is supposed to be concisely explained by a small number of salient concepts.",
                    "BoundingBox": {
                        "Width": 0.7248382568359375,
                        "Height": 0.07416196167469025,
                        "Left": 0.13706625998020172,
                        "Top": 0.3595198392868042
                    },
                    "BlockType": "LAYOUT_TEXT",
                    "Id": "fc0b1e1a-123d-4107-97a6-79030d085a66",
                    "Score": 0.8535122871398926
                },
                {
                    "Text": "Sample-wise transferability: Whether concepts extracted from a sample can be transferred to other samples.",
                    "BoundingBox": {
                        "Width": 0.7245011329650879,
                        "Height": 0.07467738538980484,
                        "Left": 0.13774386048316956,
                        "Top": 0.45485129952430725
                    },
                    "BlockType": "LAYOUT_TEXT",
                    "Id": "c11cf1a6-8e72-4211-acd2-0bac1077c552",
                    "Score": 0.8373430967330933
                },
                {
                    "Text": "8",
                    "BoundingBox": {
                        "Width": 0.010617867112159729,
                        "Height": 0.042475923895835876,
                        "Left": 0.9670968055725098,
                        "Top": 0.9274268746376038
                    },
                    "BlockType": "LAYOUT_PAGE_NUMBER",
                    "Id": "3636f81f-1e74-404f-9af8-1ad14de52f52",
                    "Score": 0.8627842664718628
                }
            ]
        }
    ]
}