{
    "MatchedRegions": [
        {
            "start_time": "00:00:01,750",
            "end_time": "00:00:04,632",
            "transcript": "To bridge the gap, we released METS-CoV data set.",
            "MatchedRegion": [
                {
                    "Text": "1 Introduction",
                    "BoundingBox": {
                        "Width": 0.1851232796907425,
                        "Height": 0.037401773035526276,
                        "Left": 0.027710797265172005,
                        "Top": 0.05102446302771568
                    },
                    "BlockType": "LAYOUT_SECTION_HEADER",
                    "Id": "a330556b-112c-4bd2-b90f-bccb07206c78",
                    "Score": 0.7887376546859741
                },
                {
                    "Text": "1.2 Contribution",
                    "BoundingBox": {
                        "Width": 0.16768276691436768,
                        "Height": 0.03158944472670555,
                        "Left": 0.02813580445945263,
                        "Top": 0.14245396852493286
                    },
                    "BlockType": "LAYOUT_SECTION_HEADER",
                    "Id": "00a01e44-6552-44ea-a552-469ececf9e5b",
                    "Score": 0.8383266925811768
                },
                {
                    "Text": "Dataset",
                    "BoundingBox": {
                        "Width": 0.06411013007164001,
                        "Height": 0.02522464282810688,
                        "Left": 0.1190263032913208,
                        "Top": 0.3952828645706177
                    },
                    "BlockType": "LAYOUT_TEXT",
                    "Id": "8feb858a-f2bc-40e5-9e12-a0ee1074d2af",
                    "Score": 0.7866487503051758
                },
                {
                    "Text": "METS-CoV (Medical Entities and Targeted Sentiments on CoVid-19-related tweets), a dataset annotated with:",
                    "BoundingBox": {
                        "Width": 0.628606915473938,
                        "Height": 0.06655193865299225,
                        "Left": 0.2565585970878601,
                        "Top": 0.24082884192466736
                    },
                    "BlockType": "LAYOUT_TEXT",
                    "Id": "110ed011-ffb6-42a8-a8a1-aacf295fbf68",
                    "Score": 0.741972029209137
                },
                {
                    "Text": "10,000 tweets",
                    "BoundingBox": {
                        "Width": 0.1321832835674286,
                        "Height": 0.027395449578762054,
                        "Left": 0.2686801850795746,
                        "Top": 0.32233476638793945
                    },
                    "BlockType": "LAYOUT_TEXT",
                    "Id": "7259dfd2-ef7c-4153-ab41-6ad8e15a498f",
                    "Score": 0.806745707988739
                },
                {
                    "Text": "7 types of entities: Disease, Drug, Symptom, Vaccine, Person, Location, and Organization.",
                    "BoundingBox": {
                        "Width": 0.703701376914978,
                        "Height": 0.031327925622463226,
                        "Left": 0.2687217891216278,
                        "Top": 0.361409991979599
                    },
                    "BlockType": "LAYOUT_TEXT",
                    "Id": "90eaaeb7-596d-4b67-ae24-22f8283252b8",
                    "Score": 0.680401086807251
                },
                {
                    "Text": "sentiments of 4 types of entities: Person, Organization, Drug, and Vaccine.",
                    "BoundingBox": {
                        "Width": 0.588422417640686,
                        "Height": 0.031165361404418945,
                        "Left": 0.2687642276287079,
                        "Top": 0.401303231716156
                    },
                    "BlockType": "LAYOUT_TEXT",
                    "Id": "4c702c28-fa4f-4a7e-9c67-b35626dc206e",
                    "Score": 0.6858571767807007
                },
                {
                    "Text": "Guidelines",
                    "BoundingBox": {
                        "Width": 0.08900683373212814,
                        "Height": 0.02543453499674797,
                        "Left": 0.1102786511182785,
                        "Top": 0.6482036113739014
                    },
                    "BlockType": "LAYOUT_TEXT",
                    "Id": "2b3b3bdc-8c08-45b7-8ae0-16ee10c68fda",
                    "Score": 0.7610640525817871
                },
                {
                    "Text": "Detailed guidelines for annotating medical entities (Disease, Drug, Symptom, Vaccine) on tweets.",
                    "BoundingBox": {
                        "Width": 0.6499955058097839,
                        "Height": 0.06682852655649185,
                        "Left": 0.25697681307792664,
                        "Top": 0.5720789432525635
                    },
                    "BlockType": "LAYOUT_TEXT",
                    "Id": "42fcdf63-1d9b-41d9-9ea0-fb4ba151c9d1",
                    "Score": 0.6748970746994019
                },
                {
                    "Text": "Benchmark",
                    "BoundingBox": {
                        "Width": 0.09478897601366043,
                        "Height": 0.025278078392148018,
                        "Left": 0.11080276221036911,
                        "Top": 0.9127707481384277
                    },
                    "BlockType": "LAYOUT_TEXT",
                    "Id": "9ba02226-20cf-4922-944b-2a4644d55805",
                    "Score": 0.7671263217926025
                },
                {
                    "Text": "Benchmarking the performance of classical machine learning models and state- of-the-art deep learning models including pre-training language models on NER and TSA tasks of METS-CoV.",
                    "BoundingBox": {
                        "Width": 0.608792781829834,
                        "Height": 0.10663367807865143,
                        "Left": 0.25661149621009827,
                        "Top": 0.785422682762146
                    },
                    "BlockType": "LAYOUT_TEXT",
                    "Id": "4bcf3e11-86fd-4c94-add1-bb9a5e6d633f",
                    "Score": 0.9648898839950562
                },
                {
                    "Text": "->",
                    "BoundingBox": {
                        "Width": 0.007673935033380985,
                        "Height": 0.013441529124975204,
                        "Left": 0.08884955197572708,
                        "Top": 0.9793319702148438
                    },
                    "BlockType": "LAYOUT_FOOTER",
                    "Id": "26c3a0ca-0ac0-409f-8d7a-477541e72921",
                    "Score": 0.7659063339233398
                },
                {
                    "Text": "3",
                    "BoundingBox": {
                        "Width": 0.0064030722714960575,
                        "Height": 0.01729859597980976,
                        "Left": 0.9168838262557983,
                        "Top": 0.9452826380729675
                    },
                    "BlockType": "LAYOUT_PAGE_NUMBER",
                    "Id": "6a5850ce-178d-4b88-ad12-45607496a609",
                    "Score": 0.7595930695533752
                }
            ]
        },
        {
            "start_time": "00:00:05,372",
            "end_time": "00:00:22,643",
            "transcript": "This data set contains 10,000 tweets with seven types of entities, including four medical entity types, such as disease, drug, symptom, and vaccine, and three general entity types, like person, location, and organization.",
            "MatchedRegion": [
                {
                    "Text": "1 Introduction",
                    "BoundingBox": {
                        "Width": 0.1851232796907425,
                        "Height": 0.037401773035526276,
                        "Left": 0.027710797265172005,
                        "Top": 0.05102446302771568
                    },
                    "BlockType": "LAYOUT_SECTION_HEADER",
                    "Id": "a330556b-112c-4bd2-b90f-bccb07206c78",
                    "Score": 0.7887376546859741
                },
                {
                    "Text": "1.2 Contribution",
                    "BoundingBox": {
                        "Width": 0.16768276691436768,
                        "Height": 0.03158944472670555,
                        "Left": 0.02813580445945263,
                        "Top": 0.14245396852493286
                    },
                    "BlockType": "LAYOUT_SECTION_HEADER",
                    "Id": "00a01e44-6552-44ea-a552-469ececf9e5b",
                    "Score": 0.8383266925811768
                },
                {
                    "Text": "Dataset",
                    "BoundingBox": {
                        "Width": 0.06411013007164001,
                        "Height": 0.02522464282810688,
                        "Left": 0.1190263032913208,
                        "Top": 0.3952828645706177
                    },
                    "BlockType": "LAYOUT_TEXT",
                    "Id": "8feb858a-f2bc-40e5-9e12-a0ee1074d2af",
                    "Score": 0.7866487503051758
                },
                {
                    "Text": "METS-CoV (Medical Entities and Targeted Sentiments on CoVid-19-related tweets), a dataset annotated with:",
                    "BoundingBox": {
                        "Width": 0.628606915473938,
                        "Height": 0.06655193865299225,
                        "Left": 0.2565585970878601,
                        "Top": 0.24082884192466736
                    },
                    "BlockType": "LAYOUT_TEXT",
                    "Id": "110ed011-ffb6-42a8-a8a1-aacf295fbf68",
                    "Score": 0.741972029209137
                },
                {
                    "Text": "10,000 tweets",
                    "BoundingBox": {
                        "Width": 0.1321832835674286,
                        "Height": 0.027395449578762054,
                        "Left": 0.2686801850795746,
                        "Top": 0.32233476638793945
                    },
                    "BlockType": "LAYOUT_TEXT",
                    "Id": "7259dfd2-ef7c-4153-ab41-6ad8e15a498f",
                    "Score": 0.806745707988739
                },
                {
                    "Text": "7 types of entities: Disease, Drug, Symptom, Vaccine, Person, Location, and Organization.",
                    "BoundingBox": {
                        "Width": 0.703701376914978,
                        "Height": 0.031327925622463226,
                        "Left": 0.2687217891216278,
                        "Top": 0.361409991979599
                    },
                    "BlockType": "LAYOUT_TEXT",
                    "Id": "90eaaeb7-596d-4b67-ae24-22f8283252b8",
                    "Score": 0.680401086807251
                },
                {
                    "Text": "sentiments of 4 types of entities: Person, Organization, Drug, and Vaccine.",
                    "BoundingBox": {
                        "Width": 0.588422417640686,
                        "Height": 0.031165361404418945,
                        "Left": 0.2687642276287079,
                        "Top": 0.401303231716156
                    },
                    "BlockType": "LAYOUT_TEXT",
                    "Id": "4c702c28-fa4f-4a7e-9c67-b35626dc206e",
                    "Score": 0.6858571767807007
                },
                {
                    "Text": "Guidelines",
                    "BoundingBox": {
                        "Width": 0.08900683373212814,
                        "Height": 0.02543453499674797,
                        "Left": 0.1102786511182785,
                        "Top": 0.6482036113739014
                    },
                    "BlockType": "LAYOUT_TEXT",
                    "Id": "2b3b3bdc-8c08-45b7-8ae0-16ee10c68fda",
                    "Score": 0.7610640525817871
                },
                {
                    "Text": "Detailed guidelines for annotating medical entities (Disease, Drug, Symptom, Vaccine) on tweets.",
                    "BoundingBox": {
                        "Width": 0.6499955058097839,
                        "Height": 0.06682852655649185,
                        "Left": 0.25697681307792664,
                        "Top": 0.5720789432525635
                    },
                    "BlockType": "LAYOUT_TEXT",
                    "Id": "42fcdf63-1d9b-41d9-9ea0-fb4ba151c9d1",
                    "Score": 0.6748970746994019
                },
                {
                    "Text": "Benchmark",
                    "BoundingBox": {
                        "Width": 0.09478897601366043,
                        "Height": 0.025278078392148018,
                        "Left": 0.11080276221036911,
                        "Top": 0.9127707481384277
                    },
                    "BlockType": "LAYOUT_TEXT",
                    "Id": "9ba02226-20cf-4922-944b-2a4644d55805",
                    "Score": 0.7671263217926025
                },
                {
                    "Text": "Benchmarking the performance of classical machine learning models and state- of-the-art deep learning models including pre-training language models on NER and TSA tasks of METS-CoV.",
                    "BoundingBox": {
                        "Width": 0.608792781829834,
                        "Height": 0.10663367807865143,
                        "Left": 0.25661149621009827,
                        "Top": 0.785422682762146
                    },
                    "BlockType": "LAYOUT_TEXT",
                    "Id": "4bcf3e11-86fd-4c94-add1-bb9a5e6d633f",
                    "Score": 0.9648898839950562
                },
                {
                    "Text": "->",
                    "BoundingBox": {
                        "Width": 0.007673935033380985,
                        "Height": 0.013441529124975204,
                        "Left": 0.08884955197572708,
                        "Top": 0.9793319702148438
                    },
                    "BlockType": "LAYOUT_FOOTER",
                    "Id": "26c3a0ca-0ac0-409f-8d7a-477541e72921",
                    "Score": 0.7659063339233398
                },
                {
                    "Text": "3",
                    "BoundingBox": {
                        "Width": 0.0064030722714960575,
                        "Height": 0.01729859597980976,
                        "Left": 0.9168838262557983,
                        "Top": 0.9452826380729675
                    },
                    "BlockType": "LAYOUT_PAGE_NUMBER",
                    "Id": "6a5850ce-178d-4b88-ad12-45607496a609",
                    "Score": 0.7595930695533752
                }
            ]
        },
        {
            "start_time": "00:00:23,464",
            "end_time": "00:00:28,307",
            "transcript": "To further investigate Twitter users' attitudes towards specific entities,",
            "MatchedRegion": [
                {
                    "Text": "1 Introduction",
                    "BoundingBox": {
                        "Width": 0.1851232796907425,
                        "Height": 0.037401773035526276,
                        "Left": 0.027710797265172005,
                        "Top": 0.05102446302771568
                    },
                    "BlockType": "LAYOUT_SECTION_HEADER",
                    "Id": "a330556b-112c-4bd2-b90f-bccb07206c78",
                    "Score": 0.7887376546859741
                },
                {
                    "Text": "1.2 Contribution",
                    "BoundingBox": {
                        "Width": 0.16768276691436768,
                        "Height": 0.03158944472670555,
                        "Left": 0.02813580445945263,
                        "Top": 0.14245396852493286
                    },
                    "BlockType": "LAYOUT_SECTION_HEADER",
                    "Id": "00a01e44-6552-44ea-a552-469ececf9e5b",
                    "Score": 0.8383266925811768
                },
                {
                    "Text": "Dataset",
                    "BoundingBox": {
                        "Width": 0.06411013007164001,
                        "Height": 0.02522464282810688,
                        "Left": 0.1190263032913208,
                        "Top": 0.3952828645706177
                    },
                    "BlockType": "LAYOUT_TEXT",
                    "Id": "8feb858a-f2bc-40e5-9e12-a0ee1074d2af",
                    "Score": 0.7866487503051758
                },
                {
                    "Text": "METS-CoV (Medical Entities and Targeted Sentiments on CoVid-19-related tweets), a dataset annotated with:",
                    "BoundingBox": {
                        "Width": 0.628606915473938,
                        "Height": 0.06655193865299225,
                        "Left": 0.2565585970878601,
                        "Top": 0.24082884192466736
                    },
                    "BlockType": "LAYOUT_TEXT",
                    "Id": "110ed011-ffb6-42a8-a8a1-aacf295fbf68",
                    "Score": 0.741972029209137
                },
                {
                    "Text": "10,000 tweets",
                    "BoundingBox": {
                        "Width": 0.1321832835674286,
                        "Height": 0.027395449578762054,
                        "Left": 0.2686801850795746,
                        "Top": 0.32233476638793945
                    },
                    "BlockType": "LAYOUT_TEXT",
                    "Id": "7259dfd2-ef7c-4153-ab41-6ad8e15a498f",
                    "Score": 0.806745707988739
                },
                {
                    "Text": "7 types of entities: Disease, Drug, Symptom, Vaccine, Person, Location, and Organization.",
                    "BoundingBox": {
                        "Width": 0.703701376914978,
                        "Height": 0.031327925622463226,
                        "Left": 0.2687217891216278,
                        "Top": 0.361409991979599
                    },
                    "BlockType": "LAYOUT_TEXT",
                    "Id": "90eaaeb7-596d-4b67-ae24-22f8283252b8",
                    "Score": 0.680401086807251
                },
                {
                    "Text": "sentiments of 4 types of entities: Person, Organization, Drug, and Vaccine.",
                    "BoundingBox": {
                        "Width": 0.588422417640686,
                        "Height": 0.031165361404418945,
                        "Left": 0.2687642276287079,
                        "Top": 0.401303231716156
                    },
                    "BlockType": "LAYOUT_TEXT",
                    "Id": "4c702c28-fa4f-4a7e-9c67-b35626dc206e",
                    "Score": 0.6858571767807007
                },
                {
                    "Text": "Guidelines",
                    "BoundingBox": {
                        "Width": 0.08900683373212814,
                        "Height": 0.02543453499674797,
                        "Left": 0.1102786511182785,
                        "Top": 0.6482036113739014
                    },
                    "BlockType": "LAYOUT_TEXT",
                    "Id": "2b3b3bdc-8c08-45b7-8ae0-16ee10c68fda",
                    "Score": 0.7610640525817871
                },
                {
                    "Text": "Detailed guidelines for annotating medical entities (Disease, Drug, Symptom, Vaccine) on tweets.",
                    "BoundingBox": {
                        "Width": 0.6499955058097839,
                        "Height": 0.06682852655649185,
                        "Left": 0.25697681307792664,
                        "Top": 0.5720789432525635
                    },
                    "BlockType": "LAYOUT_TEXT",
                    "Id": "42fcdf63-1d9b-41d9-9ea0-fb4ba151c9d1",
                    "Score": 0.6748970746994019
                },
                {
                    "Text": "Benchmark",
                    "BoundingBox": {
                        "Width": 0.09478897601366043,
                        "Height": 0.025278078392148018,
                        "Left": 0.11080276221036911,
                        "Top": 0.9127707481384277
                    },
                    "BlockType": "LAYOUT_TEXT",
                    "Id": "9ba02226-20cf-4922-944b-2a4644d55805",
                    "Score": 0.7671263217926025
                },
                {
                    "Text": "Benchmarking the performance of classical machine learning models and state- of-the-art deep learning models including pre-training language models on NER and TSA tasks of METS-CoV.",
                    "BoundingBox": {
                        "Width": 0.608792781829834,
                        "Height": 0.10663367807865143,
                        "Left": 0.25661149621009827,
                        "Top": 0.785422682762146
                    },
                    "BlockType": "LAYOUT_TEXT",
                    "Id": "4bcf3e11-86fd-4c94-add1-bb9a5e6d633f",
                    "Score": 0.9648898839950562
                },
                {
                    "Text": "->",
                    "BoundingBox": {
                        "Width": 0.007673935033380985,
                        "Height": 0.013441529124975204,
                        "Left": 0.08884955197572708,
                        "Top": 0.9793319702148438
                    },
                    "BlockType": "LAYOUT_FOOTER",
                    "Id": "26c3a0ca-0ac0-409f-8d7a-477541e72921",
                    "Score": 0.7659063339233398
                },
                {
                    "Text": "3",
                    "BoundingBox": {
                        "Width": 0.0064030722714960575,
                        "Height": 0.01729859597980976,
                        "Left": 0.9168838262557983,
                        "Top": 0.9452826380729675
                    },
                    "BlockType": "LAYOUT_PAGE_NUMBER",
                    "Id": "6a5850ce-178d-4b88-ad12-45607496a609",
                    "Score": 0.7595930695533752
                }
            ]
        },
        {
            "start_time": "00:00:29,042",
            "end_time": "00:00:37,349",
            "transcript": "Four types of entities, such as person, organization, drug, and vaccine, are selected and annotated with user sentiments.",
            "MatchedRegion": [
                {
                    "Text": "1 Introduction",
                    "BoundingBox": {
                        "Width": 0.1851232796907425,
                        "Height": 0.037401773035526276,
                        "Left": 0.027710797265172005,
                        "Top": 0.05102446302771568
                    },
                    "BlockType": "LAYOUT_SECTION_HEADER",
                    "Id": "a330556b-112c-4bd2-b90f-bccb07206c78",
                    "Score": 0.7887376546859741
                },
                {
                    "Text": "1.2 Contribution",
                    "BoundingBox": {
                        "Width": 0.16768276691436768,
                        "Height": 0.03158944472670555,
                        "Left": 0.02813580445945263,
                        "Top": 0.14245396852493286
                    },
                    "BlockType": "LAYOUT_SECTION_HEADER",
                    "Id": "00a01e44-6552-44ea-a552-469ececf9e5b",
                    "Score": 0.8383266925811768
                },
                {
                    "Text": "Dataset",
                    "BoundingBox": {
                        "Width": 0.06411013007164001,
                        "Height": 0.02522464282810688,
                        "Left": 0.1190263032913208,
                        "Top": 0.3952828645706177
                    },
                    "BlockType": "LAYOUT_TEXT",
                    "Id": "8feb858a-f2bc-40e5-9e12-a0ee1074d2af",
                    "Score": 0.7866487503051758
                },
                {
                    "Text": "METS-CoV (Medical Entities and Targeted Sentiments on CoVid-19-related tweets), a dataset annotated with:",
                    "BoundingBox": {
                        "Width": 0.628606915473938,
                        "Height": 0.06655193865299225,
                        "Left": 0.2565585970878601,
                        "Top": 0.24082884192466736
                    },
                    "BlockType": "LAYOUT_TEXT",
                    "Id": "110ed011-ffb6-42a8-a8a1-aacf295fbf68",
                    "Score": 0.741972029209137
                },
                {
                    "Text": "10,000 tweets",
                    "BoundingBox": {
                        "Width": 0.1321832835674286,
                        "Height": 0.027395449578762054,
                        "Left": 0.2686801850795746,
                        "Top": 0.32233476638793945
                    },
                    "BlockType": "LAYOUT_TEXT",
                    "Id": "7259dfd2-ef7c-4153-ab41-6ad8e15a498f",
                    "Score": 0.806745707988739
                },
                {
                    "Text": "7 types of entities: Disease, Drug, Symptom, Vaccine, Person, Location, and Organization.",
                    "BoundingBox": {
                        "Width": 0.703701376914978,
                        "Height": 0.031327925622463226,
                        "Left": 0.2687217891216278,
                        "Top": 0.361409991979599
                    },
                    "BlockType": "LAYOUT_TEXT",
                    "Id": "90eaaeb7-596d-4b67-ae24-22f8283252b8",
                    "Score": 0.680401086807251
                },
                {
                    "Text": "sentiments of 4 types of entities: Person, Organization, Drug, and Vaccine.",
                    "BoundingBox": {
                        "Width": 0.588422417640686,
                        "Height": 0.031165361404418945,
                        "Left": 0.2687642276287079,
                        "Top": 0.401303231716156
                    },
                    "BlockType": "LAYOUT_TEXT",
                    "Id": "4c702c28-fa4f-4a7e-9c67-b35626dc206e",
                    "Score": 0.6858571767807007
                },
                {
                    "Text": "Guidelines",
                    "BoundingBox": {
                        "Width": 0.08900683373212814,
                        "Height": 0.02543453499674797,
                        "Left": 0.1102786511182785,
                        "Top": 0.6482036113739014
                    },
                    "BlockType": "LAYOUT_TEXT",
                    "Id": "2b3b3bdc-8c08-45b7-8ae0-16ee10c68fda",
                    "Score": 0.7610640525817871
                },
                {
                    "Text": "Detailed guidelines for annotating medical entities (Disease, Drug, Symptom, Vaccine) on tweets.",
                    "BoundingBox": {
                        "Width": 0.6499955058097839,
                        "Height": 0.06682852655649185,
                        "Left": 0.25697681307792664,
                        "Top": 0.5720789432525635
                    },
                    "BlockType": "LAYOUT_TEXT",
                    "Id": "42fcdf63-1d9b-41d9-9ea0-fb4ba151c9d1",
                    "Score": 0.6748970746994019
                },
                {
                    "Text": "Benchmark",
                    "BoundingBox": {
                        "Width": 0.09478897601366043,
                        "Height": 0.025278078392148018,
                        "Left": 0.11080276221036911,
                        "Top": 0.9127707481384277
                    },
                    "BlockType": "LAYOUT_TEXT",
                    "Id": "9ba02226-20cf-4922-944b-2a4644d55805",
                    "Score": 0.7671263217926025
                },
                {
                    "Text": "Benchmarking the performance of classical machine learning models and state- of-the-art deep learning models including pre-training language models on NER and TSA tasks of METS-CoV.",
                    "BoundingBox": {
                        "Width": 0.608792781829834,
                        "Height": 0.10663367807865143,
                        "Left": 0.25661149621009827,
                        "Top": 0.785422682762146
                    },
                    "BlockType": "LAYOUT_TEXT",
                    "Id": "4bcf3e11-86fd-4c94-add1-bb9a5e6d633f",
                    "Score": 0.9648898839950562
                },
                {
                    "Text": "->",
                    "BoundingBox": {
                        "Width": 0.007673935033380985,
                        "Height": 0.013441529124975204,
                        "Left": 0.08884955197572708,
                        "Top": 0.9793319702148438
                    },
                    "BlockType": "LAYOUT_FOOTER",
                    "Id": "26c3a0ca-0ac0-409f-8d7a-477541e72921",
                    "Score": 0.7659063339233398
                },
                {
                    "Text": "3",
                    "BoundingBox": {
                        "Width": 0.0064030722714960575,
                        "Height": 0.01729859597980976,
                        "Left": 0.9168838262557983,
                        "Top": 0.9452826380729675
                    },
                    "BlockType": "LAYOUT_PAGE_NUMBER",
                    "Id": "6a5850ce-178d-4b88-ad12-45607496a609",
                    "Score": 0.7595930695533752
                }
            ]
        },
        {
            "start_time": "00:00:38,470",
            "end_time": "00:00:44,154",
            "transcript": "Also, we designed detailed guidelines for annotating medical entities on tweets.",
            "MatchedRegion": [
                {
                    "Text": "1 Introduction",
                    "BoundingBox": {
                        "Width": 0.1851232796907425,
                        "Height": 0.037401773035526276,
                        "Left": 0.027710797265172005,
                        "Top": 0.05102446302771568
                    },
                    "BlockType": "LAYOUT_SECTION_HEADER",
                    "Id": "a330556b-112c-4bd2-b90f-bccb07206c78",
                    "Score": 0.7887376546859741
                },
                {
                    "Text": "1.2 Contribution",
                    "BoundingBox": {
                        "Width": 0.16768276691436768,
                        "Height": 0.03158944472670555,
                        "Left": 0.02813580445945263,
                        "Top": 0.14245396852493286
                    },
                    "BlockType": "LAYOUT_SECTION_HEADER",
                    "Id": "00a01e44-6552-44ea-a552-469ececf9e5b",
                    "Score": 0.8383266925811768
                },
                {
                    "Text": "Dataset",
                    "BoundingBox": {
                        "Width": 0.06411013007164001,
                        "Height": 0.02522464282810688,
                        "Left": 0.1190263032913208,
                        "Top": 0.3952828645706177
                    },
                    "BlockType": "LAYOUT_TEXT",
                    "Id": "8feb858a-f2bc-40e5-9e12-a0ee1074d2af",
                    "Score": 0.7866487503051758
                },
                {
                    "Text": "METS-CoV (Medical Entities and Targeted Sentiments on CoVid-19-related tweets), a dataset annotated with:",
                    "BoundingBox": {
                        "Width": 0.628606915473938,
                        "Height": 0.06655193865299225,
                        "Left": 0.2565585970878601,
                        "Top": 0.24082884192466736
                    },
                    "BlockType": "LAYOUT_TEXT",
                    "Id": "110ed011-ffb6-42a8-a8a1-aacf295fbf68",
                    "Score": 0.741972029209137
                },
                {
                    "Text": "10,000 tweets",
                    "BoundingBox": {
                        "Width": 0.1321832835674286,
                        "Height": 0.027395449578762054,
                        "Left": 0.2686801850795746,
                        "Top": 0.32233476638793945
                    },
                    "BlockType": "LAYOUT_TEXT",
                    "Id": "7259dfd2-ef7c-4153-ab41-6ad8e15a498f",
                    "Score": 0.806745707988739
                },
                {
                    "Text": "7 types of entities: Disease, Drug, Symptom, Vaccine, Person, Location, and Organization.",
                    "BoundingBox": {
                        "Width": 0.703701376914978,
                        "Height": 0.031327925622463226,
                        "Left": 0.2687217891216278,
                        "Top": 0.361409991979599
                    },
                    "BlockType": "LAYOUT_TEXT",
                    "Id": "90eaaeb7-596d-4b67-ae24-22f8283252b8",
                    "Score": 0.680401086807251
                },
                {
                    "Text": "sentiments of 4 types of entities: Person, Organization, Drug, and Vaccine.",
                    "BoundingBox": {
                        "Width": 0.588422417640686,
                        "Height": 0.031165361404418945,
                        "Left": 0.2687642276287079,
                        "Top": 0.401303231716156
                    },
                    "BlockType": "LAYOUT_TEXT",
                    "Id": "4c702c28-fa4f-4a7e-9c67-b35626dc206e",
                    "Score": 0.6858571767807007
                },
                {
                    "Text": "Guidelines",
                    "BoundingBox": {
                        "Width": 0.08900683373212814,
                        "Height": 0.02543453499674797,
                        "Left": 0.1102786511182785,
                        "Top": 0.6482036113739014
                    },
                    "BlockType": "LAYOUT_TEXT",
                    "Id": "2b3b3bdc-8c08-45b7-8ae0-16ee10c68fda",
                    "Score": 0.7610640525817871
                },
                {
                    "Text": "Detailed guidelines for annotating medical entities (Disease, Drug, Symptom, Vaccine) on tweets.",
                    "BoundingBox": {
                        "Width": 0.6499955058097839,
                        "Height": 0.06682852655649185,
                        "Left": 0.25697681307792664,
                        "Top": 0.5720789432525635
                    },
                    "BlockType": "LAYOUT_TEXT",
                    "Id": "42fcdf63-1d9b-41d9-9ea0-fb4ba151c9d1",
                    "Score": 0.6748970746994019
                },
                {
                    "Text": "Benchmark",
                    "BoundingBox": {
                        "Width": 0.09478897601366043,
                        "Height": 0.025278078392148018,
                        "Left": 0.11080276221036911,
                        "Top": 0.9127707481384277
                    },
                    "BlockType": "LAYOUT_TEXT",
                    "Id": "9ba02226-20cf-4922-944b-2a4644d55805",
                    "Score": 0.7671263217926025
                },
                {
                    "Text": "Benchmarking the performance of classical machine learning models and state- of-the-art deep learning models including pre-training language models on NER and TSA tasks of METS-CoV.",
                    "BoundingBox": {
                        "Width": 0.608792781829834,
                        "Height": 0.10663367807865143,
                        "Left": 0.25661149621009827,
                        "Top": 0.785422682762146
                    },
                    "BlockType": "LAYOUT_TEXT",
                    "Id": "4bcf3e11-86fd-4c94-add1-bb9a5e6d633f",
                    "Score": 0.9648898839950562
                },
                {
                    "Text": "->",
                    "BoundingBox": {
                        "Width": 0.007673935033380985,
                        "Height": 0.013441529124975204,
                        "Left": 0.08884955197572708,
                        "Top": 0.9793319702148438
                    },
                    "BlockType": "LAYOUT_FOOTER",
                    "Id": "26c3a0ca-0ac0-409f-8d7a-477541e72921",
                    "Score": 0.7659063339233398
                },
                {
                    "Text": "3",
                    "BoundingBox": {
                        "Width": 0.0064030722714960575,
                        "Height": 0.01729859597980976,
                        "Left": 0.9168838262557983,
                        "Top": 0.9452826380729675
                    },
                    "BlockType": "LAYOUT_PAGE_NUMBER",
                    "Id": "6a5850ce-178d-4b88-ad12-45607496a609",
                    "Score": 0.7595930695533752
                }
            ]
        },
        {
            "start_time": "00:00:45,496",
            "end_time": "00:00:57,005",
            "transcript": "We benchmarked the performance of classical machine learning models and state-of-the-art deep learning models, including pre-training language models on NER and TSA tasks of machine learning.",
            "MatchedRegion": [
                {
                    "Text": "1 Introduction",
                    "BoundingBox": {
                        "Width": 0.1851232796907425,
                        "Height": 0.037401773035526276,
                        "Left": 0.027710797265172005,
                        "Top": 0.05102446302771568
                    },
                    "BlockType": "LAYOUT_SECTION_HEADER",
                    "Id": "a330556b-112c-4bd2-b90f-bccb07206c78",
                    "Score": 0.7887376546859741
                },
                {
                    "Text": "1.2 Contribution",
                    "BoundingBox": {
                        "Width": 0.16768276691436768,
                        "Height": 0.03158944472670555,
                        "Left": 0.02813580445945263,
                        "Top": 0.14245396852493286
                    },
                    "BlockType": "LAYOUT_SECTION_HEADER",
                    "Id": "00a01e44-6552-44ea-a552-469ececf9e5b",
                    "Score": 0.8383266925811768
                },
                {
                    "Text": "Dataset",
                    "BoundingBox": {
                        "Width": 0.06411013007164001,
                        "Height": 0.02522464282810688,
                        "Left": 0.1190263032913208,
                        "Top": 0.3952828645706177
                    },
                    "BlockType": "LAYOUT_TEXT",
                    "Id": "8feb858a-f2bc-40e5-9e12-a0ee1074d2af",
                    "Score": 0.7866487503051758
                },
                {
                    "Text": "METS-CoV (Medical Entities and Targeted Sentiments on CoVid-19-related tweets), a dataset annotated with:",
                    "BoundingBox": {
                        "Width": 0.628606915473938,
                        "Height": 0.06655193865299225,
                        "Left": 0.2565585970878601,
                        "Top": 0.24082884192466736
                    },
                    "BlockType": "LAYOUT_TEXT",
                    "Id": "110ed011-ffb6-42a8-a8a1-aacf295fbf68",
                    "Score": 0.741972029209137
                },
                {
                    "Text": "10,000 tweets",
                    "BoundingBox": {
                        "Width": 0.1321832835674286,
                        "Height": 0.027395449578762054,
                        "Left": 0.2686801850795746,
                        "Top": 0.32233476638793945
                    },
                    "BlockType": "LAYOUT_TEXT",
                    "Id": "7259dfd2-ef7c-4153-ab41-6ad8e15a498f",
                    "Score": 0.806745707988739
                },
                {
                    "Text": "7 types of entities: Disease, Drug, Symptom, Vaccine, Person, Location, and Organization.",
                    "BoundingBox": {
                        "Width": 0.703701376914978,
                        "Height": 0.031327925622463226,
                        "Left": 0.2687217891216278,
                        "Top": 0.361409991979599
                    },
                    "BlockType": "LAYOUT_TEXT",
                    "Id": "90eaaeb7-596d-4b67-ae24-22f8283252b8",
                    "Score": 0.680401086807251
                },
                {
                    "Text": "sentiments of 4 types of entities: Person, Organization, Drug, and Vaccine.",
                    "BoundingBox": {
                        "Width": 0.588422417640686,
                        "Height": 0.031165361404418945,
                        "Left": 0.2687642276287079,
                        "Top": 0.401303231716156
                    },
                    "BlockType": "LAYOUT_TEXT",
                    "Id": "4c702c28-fa4f-4a7e-9c67-b35626dc206e",
                    "Score": 0.6858571767807007
                },
                {
                    "Text": "Guidelines",
                    "BoundingBox": {
                        "Width": 0.08900683373212814,
                        "Height": 0.02543453499674797,
                        "Left": 0.1102786511182785,
                        "Top": 0.6482036113739014
                    },
                    "BlockType": "LAYOUT_TEXT",
                    "Id": "2b3b3bdc-8c08-45b7-8ae0-16ee10c68fda",
                    "Score": 0.7610640525817871
                },
                {
                    "Text": "Detailed guidelines for annotating medical entities (Disease, Drug, Symptom, Vaccine) on tweets.",
                    "BoundingBox": {
                        "Width": 0.6499955058097839,
                        "Height": 0.06682852655649185,
                        "Left": 0.25697681307792664,
                        "Top": 0.5720789432525635
                    },
                    "BlockType": "LAYOUT_TEXT",
                    "Id": "42fcdf63-1d9b-41d9-9ea0-fb4ba151c9d1",
                    "Score": 0.6748970746994019
                },
                {
                    "Text": "Benchmark",
                    "BoundingBox": {
                        "Width": 0.09478897601366043,
                        "Height": 0.025278078392148018,
                        "Left": 0.11080276221036911,
                        "Top": 0.9127707481384277
                    },
                    "BlockType": "LAYOUT_TEXT",
                    "Id": "9ba02226-20cf-4922-944b-2a4644d55805",
                    "Score": 0.7671263217926025
                },
                {
                    "Text": "Benchmarking the performance of classical machine learning models and state- of-the-art deep learning models including pre-training language models on NER and TSA tasks of METS-CoV.",
                    "BoundingBox": {
                        "Width": 0.608792781829834,
                        "Height": 0.10663367807865143,
                        "Left": 0.25661149621009827,
                        "Top": 0.785422682762146
                    },
                    "BlockType": "LAYOUT_TEXT",
                    "Id": "4bcf3e11-86fd-4c94-add1-bb9a5e6d633f",
                    "Score": 0.9648898839950562
                },
                {
                    "Text": "->",
                    "BoundingBox": {
                        "Width": 0.007673935033380985,
                        "Height": 0.013441529124975204,
                        "Left": 0.08884955197572708,
                        "Top": 0.9793319702148438
                    },
                    "BlockType": "LAYOUT_FOOTER",
                    "Id": "26c3a0ca-0ac0-409f-8d7a-477541e72921",
                    "Score": 0.7659063339233398
                },
                {
                    "Text": "3",
                    "BoundingBox": {
                        "Width": 0.0064030722714960575,
                        "Height": 0.01729859597980976,
                        "Left": 0.9168838262557983,
                        "Top": 0.9452826380729675
                    },
                    "BlockType": "LAYOUT_PAGE_NUMBER",
                    "Id": "6a5850ce-178d-4b88-ad12-45607496a609",
                    "Score": 0.7595930695533752
                }
            ]
        }
    ]
}